arquants/__init__.py
arquants/cerebro.py
arquants/definitions.py
arquants/helpers.py
arquants/initiator.py
arquants/sheet_envs.py
arquants/strategy.py
arquants/brokers/__init__.py
arquants/brokers/aq_broker.py
arquants/brokers/backbroker.py
arquants/brokers/bt_order_status_translator.py
arquants/demo/__init__.py
arquants/demo/demostrat.py
arquants/demo/launcher.py
arquants/directives/__init__.py
arquants/directives/directives.py
arquants/event/__init__.py
arquants/event/event_factory.py
arquants/feed/__init__.py
arquants/feed/aggregated_data.py
arquants/feed/base_data.py
arquants/feed/disaggregated_data.py
arquants/feed/hapidata.py
arquants/feed/mock_data.py
arquants/feed/top_ok_book_data.py
arquants/indicators/__init__.py
arquants/manager/__init__.py
arquants/manager/logger.py
arquants/observers/__init__.py
arquants/observers/backtesting_observer.py
arquants/observers/live_trading_observer.py
arquants/observers/position_calculator.py
arquants/sheets/__init__.py
arquants/sheets/accumulator.py
arquants/sheets/batch_logger.py
arquants/sheets/gsheet_logger.py
arquants/sheets/gsheet_reader.py
arquants/sheets/json_generator.py
arquants/sheets/queue_reader.py
arquants/sheets/sheet_item.py
arquants/sheets/sheet_manager.py
arquants/sizer/__init__.py
arquants/stores/__init__.py
arquants/stores/aq_store.py
arquants-0.0.27.dist-info/METADATA
arquants-0.0.27.dist-info/WHEEL
arquants-0.0.27.dist-info/top_level.txt
arquants-0.0.27.dist-info/RECORD
