Metadata-Version: 2.1
Name: arquants
Version: 0.0.27
Summary: arquants strategy engine
Home-page: https://gitlab.com/arquants/algorithm-engine.git
Author: TradeSpark
Author-email: info@arquants.trading
License: MIT
Platform: UNKNOWN
Requires-Dist: aq-lib (==0.0.11)
Requires-Dist: amqp (==2.2.2)
Requires-Dist: APScheduler (==3.6.0)
Requires-Dist: dateparser (==0.6.0)
Requires-Dist: enum34 (==1.1.6)
Requires-Dist: jsonpickle (==0.9.5)
Requires-Dist: kombu (==4.2.1)
Requires-Dist: logger (==1.4)
Requires-Dist: marshmallow (==3.0.0b11)
Requires-Dist: python-dateutil (==2.6.1)
Requires-Dist: pytz (==2017.3)
Requires-Dist: redis (==2.10.6)
Requires-Dist: regex (==2018.2.3)
Requires-Dist: ruamel.yaml (==0.15.35)
Requires-Dist: tzlocal (==1.5.1)
Requires-Dist: vine (==1.1.4)
Requires-Dist: certifi (==2019.6.16)
Requires-Dist: chardet (==3.0.4)
Requires-Dist: gspread (==3.1.0)
Requires-Dist: httplib2 (==0.13.1)
Requires-Dist: idna (==2.8)
Requires-Dist: oauth2client (==4.1.3)
Requires-Dist: pyasn1 (==0.4.5)
Requires-Dist: pyasn1-modules (==0.2.5)
Requires-Dist: requests (==2.22.0)
Requires-Dist: rsa (==4.0)
Requires-Dist: urllib3 (==1.25.3)
Requires-Dist: simplejson
Requires-Dist: websocket
Requires-Dist: websocket-client
Requires-Dist: google-api-python-client (==1.9.3)
Requires-Dist: wheel (==0.35.1)
Requires-Dist: backtrader (==1.9.74.123)
